unitconverter/__init__.py
unitconverter/converter.py
python_unitconverter-1.0.0.dist-info/LICENSE
python_unitconverter-1.0.0.dist-info/METADATA
python_unitconverter-1.0.0.dist-info/WHEEL
python_unitconverter-1.0.0.dist-info/top_level.txt
python_unitconverter-1.0.0.dist-info/RECORD
