Metadata-Version: 2.1
Name: python-unitconverter
Version: 1.0.0
Summary: Make conversions between various units
Author-email: Erikas Mackevičius <mackevicius.erikas1@gmail.com>
License: MIT License
Project-URL: Homepage, https://erimac2.github.io/UnitConverter/
Keywords: converter,units
Classifier: License :: OSI Approved :: MIT License
Classifier: Programming Language :: Python
Classifier: Programming Language :: Python :: 3
Requires-Python: >=3.11.0
License-File: LICENSE
Provides-Extra: dev
Requires-Dist: pytest ; extra == 'dev'
Requires-Dist: pip-tools ; extra == 'dev'
